Metadata-Version: 2.1
Name: dexscreener-apis
Version: 0.3.1
Summary: Python wrapper for the 'dexscreener.com' API
Author: 
Author-email: 
License: MIT
Keywords: dexscreener,crypto,cryptocurrency,bitcoin
Classifier: Programming Language :: Python :: 3
Classifier: License :: OSI Approved :: MIT License
Classifier: Operating System :: OS Independent
Classifier: Development Status :: 5 - Production/Stable
Classifier: Intended Audience :: Developers
Classifier: Topic :: Software Development :: Build Tools
Requires-Python: >=3.9
License-File: LICENSE
Requires-Dist: requests
Requires-Dist: pydantic
Requires-Dist: certifi
Requires-Dist: aiohttp
